src/__init__.py
src/cli.py
src/lib.py
src/llm.py
src/scriptomatic.py
scriptomatic-1.0.3.dist-info/METADATA
scriptomatic-1.0.3.dist-info/WHEEL
scriptomatic-1.0.3.dist-info/entry_points.txt
scriptomatic-1.0.3.dist-info/RECORD
