Metadata-Version: 2.1
Name: scriptomatic
Version: 1.0.3
Summary: A cli tool to generate custom Python scripts
Home-page: https://github.com/tyfiero/scriptomatic
License: MIT
Keywords: script,generator,ai,tool-use
Author: Ty Fiero
Author-email: tyfierodev@gmail.com
Requires-Python: >=3.11,<4.0
Classifier: Development Status :: 3 - Alpha
Classifier: Intended Audience :: Developers
Classifier: License :: OSI Approved :: MIT License
Classifier: Programming Language :: Python :: 3
Classifier: Programming Language :: Python :: 3.11
Classifier: Programming Language :: Python :: 3.12
Requires-Dist: dspy
Requires-Dist: openai
Requires-Dist: prompt_toolkit
Requires-Dist: pydantic
Requires-Dist: pytest
Project-URL: Repository, https://github.com/tyfiero/scriptomatic
